enums/BeamRunner.py
enums/DataflowMachineType.py
enums/DojoBeamTransformVersion.py
enums/__init__.py
pipeline_components/AbstractSchemaProvider.py
pipeline_components/AbstractStructuredTransform.py
pipeline_components/AutoRunPipeline.py
pipeline_components/PipelineOptionsProvider.py
pipeline_components/PipelineRunnerInterface.py
pipeline_components/__init__.py
pipeline_components/data_cleaning.py
pipeline_components/data_enrichment.py
pipeline_components/data_understand.py
pipeline_components/input_file.py
pipeline_components/data_cleaning/DropColumns.py
pipeline_components/data_cleaning/DropDuplicates.py
pipeline_components/data_cleaning/HandleNaNValues.py
pipeline_components/data_cleaning/KeepColumns.py
pipeline_components/data_cleaning/RemoveAccents.py
pipeline_components/data_cleaning/RenameColumns.py
pipeline_components/data_cleaning/ReplaceRegex.py
pipeline_components/data_cleaning/ReplaceValues.py
pipeline_components/data_cleaning/TrimValues.py
pipeline_components/data_cleaning/__init__.py
pipeline_components/data_enrichment/AddPeriodColumn.py
pipeline_components/data_enrichment/ColumnCopy.py
pipeline_components/data_enrichment/ColumnValueAssignment.py
pipeline_components/data_enrichment/ColumnsToDate.py
pipeline_components/data_enrichment/ColumnsToDecimal.py
pipeline_components/data_enrichment/ColumnsToFloat.py
pipeline_components/data_enrichment/ColumnsToInteger.py
pipeline_components/data_enrichment/ColumnsToLowerCase.py
pipeline_components/data_enrichment/ColumnsToString.py
pipeline_components/data_enrichment/ColumnsToUpperCase.py
pipeline_components/data_enrichment/GenericArithmeticOperation.py
pipeline_components/data_enrichment/GenericDeriveCondition.py
pipeline_components/data_enrichment/GenericDeriveConditionComplex.py
pipeline_components/data_enrichment/Join.py
pipeline_components/data_enrichment/MergeColumns.py
pipeline_components/data_enrichment/OrderFieldsByArrowSchema.py
pipeline_components/data_enrichment/OrderFieldsBySchema.py
dojo_beam_transforms-3.0.0.dist-info/METADATA
dojo_beam_transforms-3.0.0.dist-info/WHEEL
dojo_beam_transforms-3.0.0.dist-info/top_level.txt
dojo_beam_transforms-3.0.0.dist-info/RECORD
