Metadata-Version: 2.4
Name: dojo-beam-transforms
Version: 3.0.0
Requires-Dist: apache-beam[dataframe,gcp,interactive]==2.64.0
Requires-Dist: pandas==2.0.3
Requires-Dist: numpy==1.26.3
Requires-Dist: pytz==2025.2
Requires-Dist: openpyxl==3.1.5
Dynamic: requires-dist
